{
    "$schema":"./creatureset-schema.json",
    "creatures":[
        {"id":0,"type":"Goblin","maxhp": 10,"strength": 3,"speed": 5,"size": 8,"inventoryslots":2,"inventory": [
            {"id":0,"type":"Healing potion","category":"Potion"},{"id":1,"type":"Liquid courage","category":"Potion"}
        ]},
        {"id":1,"type":"Kobold","maxhp": 8,"strength": 2,"speed": 8,"size": 7,"inventoryslots":1,"inventory": [
            {"id":0,"type":"Healing potion","category":"Potion"}
        ]}
    ]
}